{"file:///c%3A/Users/jarrh/source/repos/SugarGuard.Junior/SugarGuard.Web/ViewModels/UserNotificationItem.cs":{"language":"C#","code":14,"comment":0,"blank":3},"file:///c%3A/Users/jarrh/source/repos/SugarGuard.Junior/SugarGuard.Web/ViewModels/UserPreferencesVm.cs":{"language":"C#","code":7,"comment":0,"blank":2},"file:///c%3A/Users/jarrh/source/repos/SugarGuard.Junior/SugarGuard.Web/ViewModels/TimelineItemVm.cs":{"language":"C#","code":15,"comment":36,"blank":11},"file:///c%3A/Users/jarrh/source/repos/SugarGuard.Junior/SugarGuard.Web/ViewModels/SystemStatsVm.cs":{"language":"C#","code":13,"comment":7,"blank":3},"file:///c%3A/Users/jarrh/source/repos/SugarGuard.Junior/SugarGuard.Web/ViewModels/SyncConflictVm.cs":{"language":"C#","code":11,"comment":24,"blank":8},"file:///c%3A/Users/jarrh/source/repos/SugarGuard.Junior/SugarGuard.Web/ViewModels/SyncLogVm.cs":{"language":"C#","code":12,"comment":1,"blank":2},"file:///c%3A/Users/jarrh/source/repos/SugarGuard.Junior/SugarGuard.Web/ViewModels/ParentDashboardVm.cs":{"language":"C#","code":15,"comment":28,"blank":9},"file:///c%3A/Users/jarrh/source/repos/SugarGuard.Junior/SugarGuard.Web/ViewModels/PatientListVm.cs":{"language":"C#","code":11,"comment":21,"blank":8},"file:///c%3A/Users/jarrh/source/repos/SugarGuard.Junior/SugarGuard.Web/ViewModels/MeasurementVm.cs":{"language":"C#","code":14,"comment":5,"blank":2},"file:///c%3A/Users/jarrh/source/repos/SugarGuard.Junior/SugarGuard.Web/ViewModels/LinkedAccessUserVm.cs":{"language":"C#","code":15,"comment":10,"blank":4},"file:///c%3A/Users/jarrh/source/repos/SugarGuard.Junior/SugarGuard.Web/Shared/SectionHeader.razor":{"language":"Razor","code":25,"comment":0,"blank":6},"file:///c%3A/Users/jarrh/source/repos/SugarGuard.Junior/SugarGuard.Web/Shared/StateBanner.razor.css":{"language":"CSS","code":219,"comment":20,"blank":41},"file:///c%3A/Users/jarrh/source/repos/SugarGuard.Junior/SugarGuard.Web/Shared/StateBanner.razor":{"language":"Razor","code":262,"comment":0,"blank":40},"file:///c%3A/Users/jarrh/source/repos/SugarGuard.Junior/SugarGuard.Web/ViewModels/InviteCodeVm.cs":{"language":"C#","code":13,"comment":5,"blank":3},"file:///c%3A/Users/jarrh/source/repos/SugarGuard.Junior/SugarGuard.Web/ViewModels/DoctorNoteVm.cs":{"language":"C#","code":13,"comment":2,"blank":2},"file:///c%3A/Users/jarrh/source/repos/SugarGuard.Junior/SugarGuard.Web/ViewModels/DoctorCohortSummaryVm.cs":{"language":"C#","code":7,"comment":2,"blank":2},"file:///c%3A/Users/jarrh/source/repos/SugarGuard.Junior/SugarGuard.Web/ViewModels/BackpackItemVm.cs":{"language":"C#","code":10,"comment":40,"blank":8},"file:///c%3A/Users/jarrh/source/repos/SugarGuard.Junior/SugarGuard.Web/Shared/EventTimeline.razor":{"language":"Razor","code":203,"comment":0,"blank":32},"file:///c%3A/Users/jarrh/source/repos/SugarGuard.Junior/SugarGuard.Web/Shared/EmptyStateSize.cs":{"language":"C#","code":7,"comment":3,"blank":2},"file:///c%3A/Users/jarrh/source/repos/SugarGuard.Junior/SugarGuard.Web/ViewModels/AuditLogVm.cs":{"language":"C#","code":11,"comment":24,"blank":8},"file:///c%3A/Users/jarrh/source/repos/SugarGuard.Junior/SugarGuard.Web/ViewModels/AnalyticsVm.cs":{"language":"C#","code":10,"comment":18,"blank":7},"file:///c%3A/Users/jarrh/source/repos/SugarGuard.Junior/SugarGuard.Web/ViewModels/AdminUserVm.cs":{"language":"C#","code":20,"comment":4,"blank":4},"file:///c%3A/Users/jarrh/source/repos/SugarGuard.Junior/SugarGuard.Web/Shared/BannerKind.cs":{"language":"C#","code":11,"comment":3,"blank":8},"file:///c%3A/Users/jarrh/source/repos/SugarGuard.Junior/SugarGuard.Web/ViewModels/AdminSystemStatsVm.cs":{"language":"C#","code":26,"comment":17,"blank":12},"file:///c%3A/Users/jarrh/source/repos/SugarGuard.Junior/SugarGuard.Web/ViewModels/AdminHealthVm.cs":{"language":"C#","code":15,"comment":6,"blank":4},"file:///c%3A/Users/jarrh/source/repos/SugarGuard.Junior/SugarGuard.Web/Shared/BackpackItemCard.razor":{"language":"Razor","code":678,"comment":0,"blank":106},"file:///c%3A/Users/jarrh/source/repos/SugarGuard.Junior/SugarGuard.Web/_Imports.razor":{"language":"Razor","code":18,"comment":0,"blank":1},"file:///c%3A/Users/jarrh/source/repos/SugarGuard.Junior/SugarGuard.Web/SugarGuard.Web.csproj":{"language":"XML","code":21,"comment":0,"blank":7},"file:///c%3A/Users/jarrh/source/repos/SugarGuard.Junior/SugarGuard.Web/Resources/Strings.cs":{"language":"C#","code":2,"comment":0,"blank":2},"file:///c%3A/Users/jarrh/source/repos/SugarGuard.Junior/SugarGuard.Web/Services/IAuthApiClient.cs":{"language":"C#","code":38,"comment":51,"blank":18},"file:///c%3A/Users/jarrh/source/repos/SugarGuard.Junior/SugarGuard.Web/Security/PassThroughAuthenticationHandler.cs":{"language":"C#","code":40,"comment":0,"blank":10},"file:///c%3A/Users/jarrh/source/repos/SugarGuard.Junior/SugarGuard.Web/Services/CurrentUserService.cs":{"language":"C#","code":144,"comment":24,"blank":38},"file:///c%3A/Users/jarrh/source/repos/SugarGuard.Junior/SugarGuard.Web/Services/ICurrentUserService.cs":{"language":"C#","code":22,"comment":6,"blank":14},"file:///c%3A/Users/jarrh/source/repos/SugarGuard.Junior/SugarGuard.Web/Services/ApiErrorResponse.cs":{"language":"C#","code":7,"comment":3,"blank":2},"file:///c%3A/Users/jarrh/source/repos/SugarGuard.Junior/SugarGuard.Web/Services/AdminLinkDtos.cs":{"language":"C#","code":13,"comment":6,"blank":7},"file:///c%3A/Users/jarrh/source/repos/SugarGuard.Junior/SugarGuard.Web/Services/AuthApiClient.cs":{"language":"C#","code":470,"comment":43,"blank":70},"file:///c%3A/Users/jarrh/source/repos/SugarGuard.Junior/SugarGuard.Web/Services/SugarGuardApiService.Models.cs":{"language":"C#","code":274,"comment":57,"blank":32},"file:///c%3A/Users/jarrh/source/repos/SugarGuard.Junior/SugarGuard.Web/Services/ITokenStore.cs":{"language":"C#","code":10,"comment":0,"blank":6},"file:///c%3A/Users/jarrh/source/repos/SugarGuard.Junior/SugarGuard.Web/wwwroot/js/service-worker.js":{"language":"JavaScript","code":36,"comment":2,"blank":9},"file:///c%3A/Users/jarrh/source/repos/SugarGuard.Junior/SugarGuard.Web/Services/LocalStorageTokenStore.cs":{"language":"C#","code":78,"comment":9,"blank":10},"file:///c%3A/Users/jarrh/source/repos/SugarGuard.Junior/SugarGuard.Web/wwwroot/js/interop.js":{"language":"JavaScript","code":24,"comment":13,"blank":6},"file:///c%3A/Users/jarrh/source/repos/SugarGuard.Junior/SugarGuard.Web/Services/SugarGuardApiService.Compat.cs":{"language":"C#","code":42,"comment":6,"blank":6},"file:///c%3A/Users/jarrh/source/repos/SugarGuard.Junior/SugarGuard.Web/Services/SugarGuardApiService.cs":{"language":"C#","code":1693,"comment":272,"blank":190},"file:///c%3A/Users/jarrh/source/repos/SugarGuard.Junior/SugarGuard.Web/Services/ResetPasswordResult.cs":{"language":"C#","code":10,"comment":3,"blank":5},"file:///c%3A/Users/jarrh/source/repos/SugarGuard.Junior/SugarGuard.Web/Services/JwtAuthorizationHandler.cs":{"language":"C#","code":28,"comment":0,"blank":7},"file:///c%3A/Users/jarrh/source/repos/SugarGuard.Junior/SugarGuard.Web/wwwroot/js/theme.js":{"language":"JavaScript","code":97,"comment":39,"blank":26},"file:///c%3A/Users/jarrh/source/repos/SugarGuard.Junior/SugarGuard.Web/Services/JwtAuthStateProvider.cs":{"language":"C#","code":274,"comment":48,"blank":44},"file:///c%3A/Users/jarrh/source/repos/SugarGuard.Junior/SugarGuard.Web/Utilities/SafeRedirect.cs":{"language":"C#","code":24,"comment":13,"blank":10},"file:///c%3A/Users/jarrh/source/repos/SugarGuard.Junior/SugarGuard.Web/wwwroot/js/tokenStore.js":{"language":"JavaScript","code":32,"comment":3,"blank":2},"file:///c%3A/Users/jarrh/source/repos/SugarGuard.Junior/SugarGuard.Web/wwwroot/css/admin-dashboard.css":{"language":"CSS","code":499,"comment":60,"blank":107},"file:///c%3A/Users/jarrh/source/repos/SugarGuard.Junior/SugarGuard.Web/wwwroot/js/glucose-chart.js":{"language":"JavaScript","code":757,"comment":334,"blank":108},"file:///c%3A/Users/jarrh/source/repos/SugarGuard.Junior/SugarGuard.Web/Program.cs":{"language":"C#","code":118,"comment":60,"blank":42},"file:///c%3A/Users/jarrh/source/repos/SugarGuard.Junior/SugarGuard.Web/wwwroot/css/add-note-modal.css":{"language":"CSS","code":365,"comment":40,"blank":70},"file:///c%3A/Users/jarrh/source/repos/SugarGuard.Junior/SugarGuard.Web/wwwroot/css/variables.css":{"language":"CSS","code":236,"comment":141,"blank":27},"file:///c%3A/Users/jarrh/source/repos/SugarGuard.Junior/SugarGuard.Web/wwwroot/css/sg-tokens.css":{"language":"CSS","code":161,"comment":258,"blank":30},"file:///c%3A/Users/jarrh/source/repos/SugarGuard.Junior/SugarGuard.Web/Properties/launchSettings.json":{"language":"JSON","code":23,"comment":0,"blank":1},"file:///c%3A/Users/jarrh/source/repos/SugarGuard.Junior/SugarGuard.Web/wwwroot/css/layout.css":{"language":"CSS","code":987,"comment":89,"blank":186},"file:///c%3A/Users/jarrh/source/repos/SugarGuard.Junior/SugarGuard.Web/wwwroot/css/components.css":{"language":"CSS","code":1188,"comment":111,"blank":254},"file:///c%3A/Users/jarrh/source/repos/SugarGuard.Junior/SugarGuard.Web/wwwroot/css/patient-row.css":{"language":"CSS","code":228,"comment":27,"blank":53},"file:///c%3A/Users/jarrh/source/repos/SugarGuard.Junior/SugarGuard.Web/wwwroot/css/app.css":{"language":"CSS","code":931,"comment":97,"blank":176},"file:///c%3A/Users/jarrh/source/repos/SugarGuard.Junior/SugarGuard.Web/wwwroot/css/base.css":{"language":"CSS","code":1164,"comment":242,"blank":294},"file:///c%3A/Users/jarrh/source/repos/SugarGuard.Junior/SugarGuard.Web/Pages/Doctor/NotesIndex.razor.css":{"language":"CSS","code":176,"comment":0,"blank":29},"file:///c%3A/Users/jarrh/source/repos/SugarGuard.Junior/SugarGuard.Web/Pages/Doctor/NotesIndex.razor":{"language":"Razor","code":195,"comment":0,"blank":29},"file:///c%3A/Users/jarrh/source/repos/SugarGuard.Junior/SugarGuard.Web/Pages/Doctor/Alerts.razor":{"language":"Razor","code":295,"comment":0,"blank":50},"file:///c%3A/Users/jarrh/source/repos/SugarGuard.Junior/SugarGuard.Web/Pages/Admin/Users.razor":{"language":"Razor","code":1075,"comment":0,"blank":185},"file:///c%3A/Users/jarrh/source/repos/SugarGuard.Junior/SugarGuard.Web/Pages/Admin/Dashboard.razor":{"language":"Razor","code":832,"comment":0,"blank":128},"file:///c%3A/Users/jarrh/source/repos/SugarGuard.Junior/SugarGuard.Web/Pages/Doctor/Notes.razor":{"language":"Razor","code":322,"comment":0,"blank":51},"file:///c%3A/Users/jarrh/source/repos/SugarGuard.Junior/SugarGuard.Web/Pages/Admin/DoctorRequests.razor":{"language":"Razor","code":925,"comment":0,"blank":165},"file:///c%3A/Users/jarrh/source/repos/SugarGuard.Junior/SugarGuard.Web/Pages/Doctor/Profile.razor":{"language":"Razor","code":211,"comment":0,"blank":30},"file:///c%3A/Users/jarrh/source/repos/SugarGuard.Junior/SugarGuard.Web/Pages/Admin/AuditLog.razor":{"language":"Razor","code":1096,"comment":0,"blank":191},"file:///c%3A/Users/jarrh/source/repos/SugarGuard.Junior/SugarGuard.Web/wwwroot/lib/bootstrap/dist/css/bootstrap-grid.css":{"language":"CSS","code":3886,"comment":6,"blank":193},"file:///c%3A/Users/jarrh/source/repos/SugarGuard.Junior/SugarGuard.Web/Pages/Auth/Onboarding.razor":{"language":"Razor","code":1224,"comment":5,"blank":158},"file:///c%3A/Users/jarrh/source/repos/SugarGuard.Junior/SugarGuard.Web/Pages/Doctor/Patients.razor.css":{"language":"CSS","code":704,"comment":0,"blank":116},"file:///c%3A/Users/jarrh/source/repos/SugarGuard.Junior/SugarGuard.Web/Pages/Doctor/Patients.razor":{"language":"Razor","code":672,"comment":0,"blank":87},"file:///c%3A/Users/jarrh/source/repos/SugarGuard.Junior/SugarGuard.Web/Pages/Auth/Login.razor":{"language":"Razor","code":448,"comment":0,"blank":54},"file:///c%3A/Users/jarrh/source/repos/SugarGuard.Junior/SugarGuard.Web/Pages/Doctor/PatientDetail.razor.css":{"language":"CSS","code":469,"comment":0,"blank":81},"file:///c%3A/Users/jarrh/source/repos/SugarGuard.Junior/SugarGuard.Web/wwwroot/lib/bootstrap/dist/css/bootstrap-grid.min.css":{"language":"CSS","code":1,"comment":5,"blank":0},"file:///c%3A/Users/jarrh/source/repos/SugarGuard.Junior/SugarGuard.Web/Pages/Auth/ForgotPassword.razor":{"language":"Razor","code":1017,"comment":0,"blank":144},"file:///c%3A/Users/jarrh/source/repos/SugarGuard.Junior/SugarGuard.Web/Pages/Doctor/Reports.razor":{"language":"Razor","code":363,"comment":0,"blank":56},"file:///c%3A/Users/jarrh/source/repos/SugarGuard.Junior/SugarGuard.Web/Pages/Doctor/PatientDetail.razor":{"language":"Razor","code":533,"comment":0,"blank":79},"file:///c%3A/Users/jarrh/source/repos/SugarGuard.Junior/SugarGuard.Web/wwwroot/lib/bootstrap/dist/css/bootstrap-grid.rtl.min.css":{"language":"CSS","code":1,"comment":5,"blank":0},"file:///c%3A/Users/jarrh/source/repos/SugarGuard.Junior/SugarGuard.Web/Pages/Auth/Register.razor":{"language":"Razor","code":814,"comment":0,"blank":116},"file:///c%3A/Users/jarrh/source/repos/SugarGuard.Junior/SugarGuard.Web/wwwroot/lib/bootstrap/dist/css/bootstrap-reboot.css":{"language":"CSS","code":518,"comment":14,"blank":65},"file:///c%3A/Users/jarrh/source/repos/SugarGuard.Junior/SugarGuard.Web/Pages/Auth/Verify.razor":{"language":"Razor","code":774,"comment":0,"blank":113},"file:///c%3A/Users/jarrh/source/repos/SugarGuard.Junior/SugarGuard.Web/wwwroot/lib/bootstrap/dist/css/bootstrap-reboot.min.css":{"language":"CSS","code":1,"comment":5,"blank":0},"file:///c%3A/Users/jarrh/source/repos/SugarGuard.Junior/SugarGuard.Web/Pages/Auth/ResetPassword.razor":{"language":"Razor","code":690,"comment":8,"blank":93},"file:///c%3A/Users/jarrh/source/repos/SugarGuard.Junior/SugarGuard.Web/wwwroot/lib/bootstrap/dist/css/bootstrap-grid.rtl.css":{"language":"CSS","code":3886,"comment":6,"blank":192},"file:///c%3A/Users/jarrh/source/repos/SugarGuard.Junior/SugarGuard.Web/wwwroot/lib/bootstrap/dist/css/bootstrap-utilities.min.css":{"language":"CSS","code":1,"comment":5,"blank":0},"file:///c%3A/Users/jarrh/source/repos/SugarGuard.Junior/SugarGuard.Web/wwwroot/lib/bootstrap/dist/css/bootstrap-utilities.css":{"language":"CSS","code":4891,"comment":8,"blank":503},"file:///c%3A/Users/jarrh/source/repos/SugarGuard.Junior/SugarGuard.Web/Components/_Imports.razor":{"language":"Razor","code":31,"comment":0,"blank":7},"file:///c%3A/Users/jarrh/source/repos/SugarGuard.Junior/SugarGuard.Web/wwwroot/lib/bootstrap/dist/css/bootstrap-utilities.rtl.css":{"language":"CSS","code":4887,"comment":6,"blank":500},"file:///c%3A/Users/jarrh/source/repos/SugarGuard.Junior/SugarGuard.Web/wwwroot/lib/bootstrap/dist/css/bootstrap.rtl.css":{"language":"CSS","code":11138,"comment":6,"blank":886},"file:///c%3A/Users/jarrh/source/repos/SugarGuard.Junior/SugarGuard.Web/Components/Auth/NotAuthorized.razor":{"language":"Razor","code":264,"comment":0,"blank":44},"file:///c%3A/Users/jarrh/source/repos/SugarGuard.Junior/SugarGuard.Web/Components/Auth/CodeInputComponent.razor":{"language":"Razor","code":447,"comment":0,"blank":79},"file:///c%3A/Users/jarrh/source/repos/SugarGuard.Junior/SugarGuard.Web/wwwroot/lib/bootstrap/dist/css/bootstrap.min.css":{"language":"CSS","code":2,"comment":4,"blank":0},"file:///c%3A/Users/jarrh/source/repos/SugarGuard.Junior/SugarGuard.Web/wwwroot/lib/bootstrap/dist/css/bootstrap.css":{"language":"CSS","code":11136,"comment":24,"blank":897},"file:///c%3A/Users/jarrh/source/repos/SugarGuard.Junior/SugarGuard.Web/Models/Analytics/AnalyticsModels.cs":{"language":"C#","code":51,"comment":15,"blank":27},"file:///c%3A/Users/jarrh/source/repos/SugarGuard.Junior/SugarGuard.Web/Components/Routes.razor":{"language":"Razor","code":22,"comment":0,"blank":1},"file:///c%3A/Users/jarrh/source/repos/SugarGuard.Junior/SugarGuard.Web/wwwroot/lib/bootstrap/dist/css/bootstrap-utilities.rtl.min.css":{"language":"CSS","code":1,"comment":5,"blank":0},"file:///c%3A/Users/jarrh/source/repos/SugarGuard.Junior/SugarGuard.Web/Components/Auth/PasswordStrengthIndicator.razor":{"language":"Razor","code":236,"comment":0,"blank":46},"file:///c%3A/Users/jarrh/source/repos/SugarGuard.Junior/SugarGuard.Web/Components/Auth/RedirectToLogin.razor":{"language":"Razor","code":93,"comment":0,"blank":17},"file:///c%3A/Users/jarrh/source/repos/SugarGuard.Junior/SugarGuard.Web/Components/Shared/AddNoteModal.razor":{"language":"Razor","code":385,"comment":0,"blank":55},"file:///c%3A/Users/jarrh/source/repos/SugarGuard.Junior/SugarGuard.Web/wwwroot/lib/bootstrap/dist/css/bootstrap-reboot.rtl.min.css":{"language":"CSS","code":1,"comment":5,"blank":0},"file:///c%3A/Users/jarrh/source/repos/SugarGuard.Junior/SugarGuard.Web/wwwroot/lib/bootstrap/dist/js/bootstrap.esm.min.js":{"language":"JavaScript","code":1,"comment":6,"blank":0},"file:///c%3A/Users/jarrh/source/repos/SugarGuard.Junior/SugarGuard.Web/wwwroot/lib/bootstrap/dist/js/bootstrap.esm.js":{"language":"JavaScript","code":3568,"comment":578,"blank":302},"file:///c%3A/Users/jarrh/source/repos/SugarGuard.Junior/SugarGuard.Web/Components/Shared/AiRecommendationCard.razor":{"language":"Razor","code":517,"comment":0,"blank":88},"file:///c%3A/Users/jarrh/source/repos/SugarGuard.Junior/SugarGuard.Web/wwwroot/lib/bootstrap/dist/js/bootstrap.min.js":{"language":"JavaScript","code":1,"comment":6,"blank":0},"file:///c%3A/Users/jarrh/source/repos/SugarGuard.Junior/SugarGuard.Web/Components/Pages/Index.razor":{"language":"Razor","code":926,"comment":0,"blank":122},"file:///c%3A/Users/jarrh/source/repos/SugarGuard.Junior/SugarGuard.Web/Components/Pages/Error.razor":{"language":"Razor","code":29,"comment":0,"blank":8},"file:///c%3A/Users/jarrh/source/repos/SugarGuard.Junior/SugarGuard.Web/Components/Pages/Parent/ParentSettings.razor":{"language":"Razor","code":10,"comment":0,"blank":2},"file:///c%3A/Users/jarrh/source/repos/SugarGuard.Junior/SugarGuard.Web/Components/Pages/Parent/ParentMeasurements.razor":{"language":"Razor","code":10,"comment":0,"blank":2},"file:///c%3A/Users/jarrh/source/repos/SugarGuard.Junior/SugarGuard.Web/Components/Pages/Parent/ParentNutrition.razor":{"language":"Razor","code":10,"comment":0,"blank":2},"file:///c%3A/Users/jarrh/source/repos/SugarGuard.Junior/SugarGuard.Web/Components/Pages/Parent/ParentExport.razor":{"language":"Razor","code":10,"comment":0,"blank":2},"file:///c%3A/Users/jarrh/source/repos/SugarGuard.Junior/SugarGuard.Web/Components/Pages/Parent/ParentDoctor.razor":{"language":"Razor","code":10,"comment":0,"blank":2},"file:///c%3A/Users/jarrh/source/repos/SugarGuard.Junior/SugarGuard.Web/Components/Shared/LoadingSkeleton.razor.css":{"language":"CSS","code":111,"comment":10,"blank":20},"file:///c%3A/Users/jarrh/source/repos/SugarGuard.Junior/SugarGuard.Web/Components/Shared/RoleBadge.razor.css":{"language":"CSS","code":94,"comment":13,"blank":16},"file:///c%3A/Users/jarrh/source/repos/SugarGuard.Junior/SugarGuard.Web/wwwroot/lib/bootstrap/dist/css/bootstrap.rtl.min.css":{"language":"CSS","code":2,"comment":4,"blank":0},"file:///c%3A/Users/jarrh/source/repos/SugarGuard.Junior/SugarGuard.Web/Components/Shared/SessionExpiredDialog.razor":{"language":"Razor","code":385,"comment":0,"blank":73},"file:///c%3A/Users/jarrh/source/repos/SugarGuard.Junior/SugarGuard.Web/Components/Shared/RoleBadge.razor":{"language":"Razor","code":122,"comment":0,"blank":24},"file:///c%3A/Users/jarrh/source/repos/SugarGuard.Junior/SugarGuard.Web/Components/Shared/PatientRow.razor":{"language":"Razor","code":237,"comment":0,"blank":24},"file:///c%3A/Users/jarrh/source/repos/SugarGuard.Junior/SugarGuard.Web/Components/Shared/PatientCard.razor":{"language":"Razor","code":470,"comment":0,"blank":78},"file:///c%3A/Users/jarrh/source/repos/SugarGuard.Junior/SugarGuard.Web/Components/Shared/SkeletonVariant.cs":{"language":"C#","code":12,"comment":3,"blank":9},"file:///c%3A/Users/jarrh/source/repos/SugarGuard.Junior/SugarGuard.Web/Components/Shared/PageHeader.razor.css":{"language":"CSS","code":185,"comment":15,"blank":29},"file:///c%3A/Users/jarrh/source/repos/SugarGuard.Junior/SugarGuard.Web/Components/Shared/SyncBanner.razor.css":{"language":"CSS","code":193,"comment":18,"blank":34},"file:///c%3A/Users/jarrh/source/repos/SugarGuard.Junior/SugarGuard.Web/Components/Shared/SyncBanner.razor":{"language":"Razor","code":248,"comment":0,"blank":38},"file:///c%3A/Users/jarrh/source/repos/SugarGuard.Junior/SugarGuard.Web/wwwroot/lib/bootstrap/dist/js/bootstrap.bundle.js":{"language":"JavaScript","code":5064,"comment":655,"blank":596},"file:///c%3A/Users/jarrh/source/repos/SugarGuard.Junior/SugarGuard.Web/Components/Shared/ThemeToggle.razor":{"language":"Razor","code":262,"comment":0,"blank":44},"file:///c%3A/Users/jarrh/source/repos/SugarGuard.Junior/SugarGuard.Web/Components/Shared/StatusChip.razor":{"language":"Razor","code":42,"comment":0,"blank":8},"file:///c%3A/Users/jarrh/source/repos/SugarGuard.Junior/SugarGuard.Web/Components/Shared/StatCard.razor":{"language":"Razor","code":414,"comment":0,"blank":55},"file:///c%3A/Users/jarrh/source/repos/SugarGuard.Junior/SugarGuard.Web/Components/Shared/PageHeader.razor":{"language":"Razor","code":144,"comment":0,"blank":36},"file:///c%3A/Users/jarrh/source/repos/SugarGuard.Junior/SugarGuard.Web/Components/Shared/TimelineItem.razor":{"language":"Razor","code":153,"comment":0,"blank":16},"file:///c%3A/Users/jarrh/source/repos/SugarGuard.Junior/SugarGuard.Web/Components/Shared/TirProgressBar.razor":{"language":"Razor","code":298,"comment":0,"blank":49},"file:///c%3A/Users/jarrh/source/repos/SugarGuard.Junior/SugarGuard.Web/wwwroot/lib/bootstrap/dist/js/bootstrap.js":{"language":"JavaScript","code":3604,"comment":584,"blank":307},"file:///c%3A/Users/jarrh/source/repos/SugarGuard.Junior/SugarGuard.Web/Components/Shared/NavItem.razor.css":{"language":"CSS","code":54,"comment":11,"blank":10},"file:///c%3A/Users/jarrh/source/repos/SugarGuard.Junior/SugarGuard.Web/Components/Shared/ModalVariant.cs":{"language":"C#","code":7,"comment":3,"blank":2},"file:///c%3A/Users/jarrh/source/repos/SugarGuard.Junior/SugarGuard.Web/Components/Pages/Parent/ParentBackpack.razor":{"language":"Razor","code":10,"comment":0,"blank":2},"file:///c%3A/Users/jarrh/source/repos/SugarGuard.Junior/SugarGuard.Web/Components/Shared/NavItem.razor":{"language":"Razor","code":42,"comment":0,"blank":8},"file:///c%3A/Users/jarrh/source/repos/SugarGuard.Junior/SugarGuard.Web/Components/Shared/MeasurementTable.razor":{"language":"Razor","code":611,"comment":0,"blank":100},"file:///c%3A/Users/jarrh/source/repos/SugarGuard.Junior/SugarGuard.Web/Components/Shared/LoadingSpinner.razor":{"language":"Razor","code":174,"comment":0,"blank":32},"file:///c%3A/Users/jarrh/source/repos/SugarGuard.Junior/SugarGuard.Web/Components/Shared/LoadingSkeleton.razor":{"language":"Razor","code":142,"comment":0,"blank":11},"file:///c%3A/Users/jarrh/source/repos/SugarGuard.Junior/SugarGuard.Web/Components/Shared/GlucoseStatusBadge.razor":{"language":"Razor","code":203,"comment":0,"blank":38},"file:///c%3A/Users/jarrh/source/repos/SugarGuard.Junior/SugarGuard.Web/Components/Shared/InviteCodeModal.razor":{"language":"Razor","code":281,"comment":0,"blank":36},"file:///c%3A/Users/jarrh/source/repos/SugarGuard.Junior/SugarGuard.Web/Components/Shared/GlucoseChart.razor.css":{"language":"CSS","code":164,"comment":9,"blank":28},"file:///c%3A/Users/jarrh/source/repos/SugarGuard.Junior/SugarGuard.Web/Components/Shared/DataTable.razor":{"language":"Razor","code":307,"comment":0,"blank":55},"file:///c%3A/Users/jarrh/source/repos/SugarGuard.Junior/SugarGuard.Web/Components/Shared/EmptyState.razor":{"language":"Razor","code":311,"comment":0,"blank":61},"file:///c%3A/Users/jarrh/source/repos/SugarGuard.Junior/SugarGuard.Web/Components/Shared/GlucoseChart.razor":{"language":"Razor","code":301,"comment":0,"blank":59},"file:///c%3A/Users/jarrh/source/repos/SugarGuard.Junior/SugarGuard.Web/Components/Shared/DoctorNoteCard.razor":{"language":"Razor","code":202,"comment":0,"blank":31},"file:///c%3A/Users/jarrh/source/repos/SugarGuard.Junior/SugarGuard.Web/Components/Pages/Doctor/NoteEditor.razor":{"language":"Razor","code":811,"comment":0,"blank":127},"file:///c%3A/Users/jarrh/source/repos/SugarGuard.Junior/SugarGuard.Web/Components/Shared/ConfirmationDialog.razor":{"language":"Razor","code":161,"comment":0,"blank":14},"file:///c%3A/Users/jarrh/source/repos/SugarGuard.Junior/SugarGuard.Web/Components/Pages/Doctor/Dashboard.razor":{"language":"Razor","code":520,"comment":0,"blank":87},"file:///c%3A/Users/jarrh/source/repos/SugarGuard.Junior/SugarGuard.Web/Components/Pages/Doctor/CohortStats.razor":{"language":"Razor","code":837,"comment":0,"blank":130},"file:///c%3A/Users/jarrh/source/repos/SugarGuard.Junior/SugarGuard.Web/Components/Shared/ChildSelector.razor":{"language":"Razor","code":657,"comment":0,"blank":94},"file:///c%3A/Users/jarrh/source/repos/SugarGuard.Junior/SugarGuard.Web/Components/Shared/BreadcrumbItem.cs":{"language":"C#","code":2,"comment":3,"blank":2},"file:///c%3A/Users/jarrh/source/repos/SugarGuard.Junior/SugarGuard.Web/Components/Pages/Admin/AdminFaq.razor":{"language":"Razor","code":378,"comment":0,"blank":48},"file:///c%3A/Users/jarrh/source/repos/SugarGuard.Junior/SugarGuard.Web/Components/Pages/Admin/AdminExportLogs.razor":{"language":"Razor","code":229,"comment":0,"blank":27},"file:///c%3A/Users/jarrh/source/repos/SugarGuard.Junior/SugarGuard.Web/Components/Pages/Admin/AdminRoles.razor":{"language":"Razor","code":186,"comment":0,"blank":29},"file:///c%3A/Users/jarrh/source/repos/SugarGuard.Junior/SugarGuard.Web/Components/Shared/AlertBanner.razor":{"language":"Razor","code":473,"comment":0,"blank":76},"file:///c%3A/Users/jarrh/source/repos/SugarGuard.Junior/SugarGuard.Web/Components/Pages/Admin/LinkManager.razor.css":{"language":"CSS","code":343,"comment":9,"blank":60},"file:///c%3A/Users/jarrh/source/repos/SugarGuard.Junior/SugarGuard.Web/Components/Pages/Admin/SystemStats.razor.css":{"language":"CSS","code":333,"comment":10,"blank":65},"file:///c%3A/Users/jarrh/source/repos/SugarGuard.Junior/SugarGuard.Web/Components/Pages/Admin/SystemStats.razor":{"language":"Razor","code":404,"comment":0,"blank":57},"file:///c%3A/Users/jarrh/source/repos/SugarGuard.Junior/SugarGuard.Web/Components/Pages/Admin/AdminTokens.razor":{"language":"Razor","code":353,"comment":0,"blank":56},"file:///c%3A/Users/jarrh/source/repos/SugarGuard.Junior/SugarGuard.Web/Components/Pages/Admin/AdminSyncLogs.razor":{"language":"Razor","code":279,"comment":0,"blank":29},"file:///c%3A/Users/jarrh/source/repos/SugarGuard.Junior/SugarGuard.Web/Components/Pages/Admin/LinkManager.razor":{"language":"Razor","code":692,"comment":0,"blank":86},"file:///c%3A/Users/jarrh/source/repos/SugarGuard.Junior/SugarGuard.Web/wwwroot/lib/bootstrap/dist/css/bootstrap-reboot.rtl.css":{"language":"CSS","code":524,"comment":6,"blank":64},"file:///c%3A/Users/jarrh/source/repos/SugarGuard.Junior/SugarGuard.Web/Components/Layout/EmptyLayout.razor":{"language":"Razor","code":5,"comment":0,"blank":1},"file:///c%3A/Users/jarrh/source/repos/SugarGuard.Junior/SugarGuard.Web/Components/Layout/AdminNavMenu.razor":{"language":"Razor","code":27,"comment":0,"blank":4},"file:///c%3A/Users/jarrh/source/repos/SugarGuard.Junior/SugarGuard.Web/Components/Layout/MainLayout.razor":{"language":"Razor","code":443,"comment":0,"blank":48},"file:///c%3A/Users/jarrh/source/repos/SugarGuard.Junior/SugarGuard.Web/Components/Layout/DashboardLayout.razor":{"language":"Razor","code":718,"comment":0,"blank":104},"file:///c%3A/Users/jarrh/source/repos/SugarGuard.Junior/SugarGuard.Web/Components/Layout/MainLayout.razor.css":{"language":"CSS","code":713,"comment":20,"blank":105},"file:///c%3A/Users/jarrh/source/repos/SugarGuard.Junior/SugarGuard.Web/Components/Admin/UserRow.razor":{"language":"Razor","code":190,"comment":0,"blank":50},"file:///c%3A/Users/jarrh/source/repos/SugarGuard.Junior/SugarGuard.Web/Components/Layout/AdminLayout.razor":{"language":"Razor","code":31,"comment":0,"blank":3},"file:///c%3A/Users/jarrh/source/repos/SugarGuard.Junior/SugarGuard.Web/Components/Layout/ParentLayout.razor":{"language":"Razor","code":361,"comment":0,"blank":50},"file:///c%3A/Users/jarrh/source/repos/SugarGuard.Junior/SugarGuard.Web/wwwroot/lib/bootstrap/dist/js/bootstrap.bundle.min.js":{"language":"JavaScript","code":1,"comment":6,"blank":0},"file:///c%3A/Users/jarrh/source/repos/SugarGuard.Junior/SugarGuard.Web/Models/Charts/GlucoseChartPoint.cs":{"language":"C#","code":6,"comment":3,"blank":2},"file:///c%3A/Users/jarrh/source/repos/SugarGuard.Junior/SugarGuard.Web/Models/Charts/GlucoseChartViewModel.cs":{"language":"C#","code":14,"comment":3,"blank":11},"file:///c%3A/Users/jarrh/source/repos/SugarGuard.Junior/SugarGuard.Web/Models/Charts/GlucoseChartPayload.cs":{"language":"C#","code":13,"comment":3,"blank":10},"file:///c%3A/Users/jarrh/source/repos/SugarGuard.Junior/SugarGuard.Web/Components/Layout/NavMenu.razor.css":{"language":"CSS","code":225,"comment":8,"blank":36},"file:///c%3A/Users/jarrh/source/repos/SugarGuard.Junior/SugarGuard.Web/Components/Layout/NavMenu.razor":{"language":"Razor","code":269,"comment":0,"blank":29},"file:///c%3A/Users/jarrh/source/repos/SugarGuard.Junior/SugarGuard.Web/Models/Auth/AuthModels.cs":{"language":"C#","code":41,"comment":19,"blank":19},"file:///c%3A/Users/jarrh/source/repos/SugarGuard.Junior/SugarGuard.Web/App.razor":{"language":"Razor","code":51,"comment":7,"blank":13},"file:///c%3A/Users/jarrh/source/repos/SugarGuard.Junior/SugarGuard.Web/Pages/Parent/SyncConflicts.razor.css":{"language":"CSS","code":410,"comment":0,"blank":73},"file:///c%3A/Users/jarrh/source/repos/SugarGuard.Junior/SugarGuard.Web/Pages/Parent/Timeline.razor.css":{"language":"CSS","code":773,"comment":20,"blank":156},"file:///c%3A/Users/jarrh/source/repos/SugarGuard.Junior/SugarGuard.Web/Pages/Parent/LinkChild.razor":{"language":"Razor","code":237,"comment":0,"blank":36},"file:///c%3A/Users/jarrh/source/repos/SugarGuard.Junior/SugarGuard.Web/Pages/Parent/Timeline.razor":{"language":"Razor","code":957,"comment":11,"blank":120},"file:///c%3A/Users/jarrh/source/repos/SugarGuard.Junior/SugarGuard.Web/Pages/Parent/SyncConflicts.razor":{"language":"Razor","code":529,"comment":6,"blank":46},"file:///c%3A/Users/jarrh/source/repos/SugarGuard.Junior/SugarGuard.Web/Pages/Parent/Links.razor":{"language":"Razor","code":1155,"comment":0,"blank":153},"file:///c%3A/Users/jarrh/source/repos/SugarGuard.Junior/SugarGuard.Web/Pages/Parent/Dashboard.razor.css":{"language":"CSS","code":1108,"comment":32,"blank":200},"file:///c%3A/Users/jarrh/source/repos/SugarGuard.Junior/SugarGuard.Web/Pages/Parent/Dashboard.razor":{"language":"Razor","code":1940,"comment":0,"blank":189},"file:///c%3A/Users/jarrh/source/repos/SugarGuard.Junior/SugarGuard.Web/Pages/Parent/Analytics.razor":{"language":"Razor","code":580,"comment":0,"blank":69}}